{"firebase": {"auth": {"isEmpty": true, "isLoaded": true}, "authError": null, "data": {}, "errors": [], "isInitializing": false, "listeners": {"allIds": [Array], "byId": [Object]}, "ordered": {}, "profile": {"isEmpty": true, "isLoaded": true}, "requested": {}, "requesting": {}, "timestamps": {}}, "firestore": {"composite": undefined, "data": {}, "errors": {"allIds": [Array], "byQuery": [Object]}, "listeners": {"allIds": [Array], "byId": [Object]}, "ordered": {}, "queries": {}, "status": {"requested": [Object], "requesting": [Object], "timestamps": [Object]}}, "loading": {"loading": false}} {"firebase": {"auth": {"isEmpty": true, "isLoaded": true}, "authError": null, "data": {}, "errors": [], "isInitializing": false, "listeners": {"allIds": [Array], "byId": [Object]}, "ordered": {}, "profile": {"isEmpty": true, "isLoaded": true}, "requested": {}, "requesting": {}, "timestamps": {}}, "firestore": {"composite": undefined, "data": {}, "errors": {"allIds": [Array], "byQuery": [Object]}, "listeners": {"allIds": [Array], "byId": [Object]}, "ordered": {}, "queries": {}, "status": {"requested": [Object], "requesting": [Object], "timestamps": [Object]}}, "loading": {"loading": false}}